ecmsapi/__init__.py
ecmsapi/conn.py
ecmsapi/queries.py
ecmsapi/tables/__init__.py
ecmsapi/tables/_base.py
ecmsapi/tables/models.py
ecmsapi/tables/AccountsPayable/__init__.py
ecmsapi/tables/AccountsPayable/models.py
ecmsapi/tables/AccountsReceivable/__init__.py
ecmsapi/tables/AccountsReceivable/models.py
ecmsapi/tables/Equipment/__init__.py
ecmsapi/tables/Equipment/models.py
ecmsapi/tables/GeneralLedger/__init__.py
ecmsapi/tables/GeneralLedger/models.py
ecmsapi/tables/HumanResources/__init__.py
ecmsapi/tables/HumanResources/models.py
ecmsapi/tables/JobCosting/__init__.py
ecmsapi/tables/JobCosting/models.py
ecms_api-2.0.1.dist-info/LICENSE
ecms_api-2.0.1.dist-info/METADATA
ecms_api-2.0.1.dist-info/WHEEL
ecms_api-2.0.1.dist-info/top_level.txt
ecms_api-2.0.1.dist-info/RECORD
