Metadata-Version: 2.1
Name: ecms-api
Version: 2.0.1
Summary: A python integration to allow for quickly sending queries directly to the as400
Author: Johnny Whitworth
Author-email: jwhitworth@arizonapipeline.com
Project-URL: ecms_api, https://github.com/Poseidon-Dev/ecms-api
Classifier: Development Status :: 4 - Beta
Classifier: Intended Audience :: Other Audience
Classifier: License :: OSI Approved :: MIT License
Classifier: Natural Language :: English
Classifier: Programming Language :: Python :: 3.9
Classifier: Operating System :: Microsoft :: Windows
Requires-Python: >=3.1
License-File: LICENSE
Requires-Dist: pandas
Requires-Dist: pyodbc
